agent_skills_upd/__init__.py
agent_skills_upd/exceptions.py
agent_skills_upd/fetcher.py
agent_skills_upd/github.py
agent_skills_upd/scaffold.py
agent_skills_upd/cli/__init__.py
agent_skills_upd/cli/agent.py
agent_skills_upd/cli/command.py
agent_skills_upd/cli/common.py
agent_skills_upd/cli/create.py
agent_skills_upd/cli/skill.py
agent_skills_upd-0.1.1.dist-info/METADATA
agent_skills_upd-0.1.1.dist-info/WHEEL
agent_skills_upd-0.1.1.dist-info/entry_points.txt
agent_skills_upd-0.1.1.dist-info/RECORD
