Metadata-Version: 2.4
Name: agent-skills-upd
Version: 0.1.1
Summary: Update your Claude Code, Codex, OpenCode, Amp, ClawdBot skills
License-Expression: MIT
Requires-Python: >=3.10
Requires-Dist: httpx>=0.27
Requires-Dist: python-frontmatter>=1.0
Requires-Dist: pyyaml>=6.0
Requires-Dist: rich>=13.0
Requires-Dist: typer>=0.12
Provides-Extra: dev
Requires-Dist: mypy>=1.0; extra == 'dev'
Requires-Dist: pytest>=7.0; extra == 'dev'
Requires-Dist: ruff>=0.1.0; extra == 'dev'
Requires-Dist: types-pyyaml>=6.0; extra == 'dev'
